{
    "type": "object",
    "properties": {
        "Action": {
            "required": true,
            "type": "string"
        },
        "Version": {
            "required": true,
            "type": "string"
        },
        "requestBody": {
            "properties": {
                "commitSpecifier": {
                    "description": "The fully-quaified reference that identifies the commit that contains the file. For example, you could specify a full commit ID, a tag, a branch name, or a reference such as refs/heads/master. If none is provided, then the head commit will be used.",
                    "type": "string"
                },
                "filePath": {
                    "description": "The fully-qualified path to the file, including the full name and extension of the file. For example, /examples/file.md is the fully-qualified path to a file named file.md in a folder named examples.",
                    "type": "string"
                },
                "repositoryName": {
                    "description": "The name of the repository that contains the file.",
                    "maxLength": 100,
                    "minLength": 1,
                    "pattern": "[\\w\\.-]+",
                    "type": "string"
                }
            },
            "required": [
                "repositoryName",
                "filePath"
            ],
            "type": "object"
        },
        "X_Amz_Content_Sha256": {
            "required": false,
            "type": "string"
        },
        "X_Amz_Date": {
            "required": false,
            "type": "string"
        },
        "X_Amz_Algorithm": {
            "required": false,
            "type": "string"
        },
        "X_Amz_Credential": {
            "required": false,
            "type": "string"
        },
        "X_Amz_Security_Token": {
            "required": false,
            "type": "string"
        },
        "X_Amz_Signature": {
            "required": false,
            "type": "string"
        },
        "X_Amz_SignedHeaders": {
            "required": false,
            "type": "string"
        }
    }
}